llm_runner-0.2.12.dist-info/METADATA
llm_runner-0.2.12.dist-info/WHEEL
llm_runner-0.2.12.dist-info/licenses/LICENSE
llm_runner/__init__.py
llm_runner/llm_runner.cpython-313-darwin.so
llm_runner-0.2.12.dist-info/RECORD
